mst/core/__init__.py
mst/core/local_env.py
mst/core/setuid.py
mst/core/usage_logger.py
mst_core-1.2.0.dist-info/METADATA
mst_core-1.2.0.dist-info/WHEEL
mst_core-1.2.0.dist-info/top_level.txt
mst_core-1.2.0.dist-info/RECORD
