Metadata-Version: 2.4
Name: mst-core
Version: 1.2.0
Summary: Core modules for use with Missouri S&T's Python apps.
Author-email: Missouri University of Science and Technology - Information Technology <it-ai@mst.edu>
Requires-Python: >=3.8
Requires-Dist: ttl-cache
